[{"network_depth":0,"total_gates":9,"network_size":0,"preprocess_weight":0},{"network_depth":0,"total_gates":9,"network_size":0,"preprocess_weight":0},{"network_depth":53,"total_gates":7161,"network_size":162220,"preprocess_weight":6020200},{"network_depth":53,"total_gates":18188,"network_size":271024,"preprocess_weight":11682400},{"network_depth":59,"total_gates":18966,"network_size":275121,"preprocess_weight":11700650},{"network_depth":59,"total_gates":18989,"network_size":275121,"preprocess_weight":11700650},{"network_depth":60,"total_gates":18990,"network_size":275249,"preprocess_weight":11705650},{"network_depth":60,"total_gates":19640,"network_size":279346,"preprocess_weight":11723900},{"network_depth":60,"total_gates":19640,"network_size":279346,"preprocess_weight":11723900},{"network_depth":60,"total_gates":19641,"network_size":279346,"preprocess_weight":11723900},{"network_depth":60,"total_gates":19643,"network_size":279346,"preprocess_weight":11723900},{"network_depth":60,"total_gates":19645,"network_size":279346,"preprocess_weight":11723900},{"network_depth":61,"total_gates":21560,"network_size":353202,"preprocess_weight":14143100},{"network_depth":61,"total_gates":21561,"network_size":353202,"preprocess_weight":14143100},{"network_depth":61,"total_gates":21562,"network_size":353202,"preprocess_weight":14143100},{"network_depth":61,"total_gates":23537,"network_size":427122,"preprocess_weight":16562300}]